Workbook
Name aporte: App!$D$17

Sheet App
B14: INVESTIMENTO MENSAL | F14: Configurações
B15: Quanto investir por mês? | C15: 500 | F15: Salário | G15: 5000
B16: Por quanto tempo investir? (em anos) | C16: 5 | F16: Rendimentos Carteira | G16: 0.01079
B17: Taxa de rendimento ao mês | C17: 0.01079 | F17: Sugestão de investimento | G17: =G15*30% -> 1500
B18: Patrimônio acumulado | C18: =FV($C$17,$C$16*12,$C$15)*-1 -> 41888.457
B19: Dividendos mensais | C19: =$C$18*$C$17 -> 451.97645
B22: Cenários (em anos) | D22: Dividendo
B23: 2 | C23: =FV($C$17,B23*12,$C$15)*-1 -> 13613.814 | D23: =C23*G16 -> 146.89305
B24: 5 | C24: =FV($C$17,B24*12,$C$15)*-1 -> 41888.457 | D24: =C24*1% -> 418.88457
B25: 10 | C25: =FV($C$17,B25*12,$C$15)*-1 -> 121642.11 | D25: =C25*1% -> 1216.4211
B26: 20 | C26: =FV($C$17,B26*12,$C$15)*-1 -> 562599.2 | D26: =C26*1% -> 5625.992
B27: 30 | C27: =FV($C$17,B27*12,$C$15)*-1 -> 2161084.8 | D27: =C27*1% -> 21610.848
B30: PERFIL | C30: Moderado
B31: VALOR A SER INVESTIDO POR MÊS | C31: 350
B33: TIPO DE FII | C33: Percentual Sugerido | D33: Valores
B34: PAPEL | C34: =VLOOKUP($C$30&"-"&B34,Base!$A:$D,4,FALSE) -> 0.32 | D34: =C34*$C$31 -> 112
B35: TIJOLO | C35: =VLOOKUP($C$30&"-"&B35,Base!$A:$D,4,FALSE) -> 0.35 | D35: =C35*$C$31 -> 122.5
B36: HÍBRIDOS | C36: =VLOOKUP($C$30&"-"&B36,Base!$A:$D,4,FALSE) -> 0.08 | D36: =C36*$C$31 -> 28
B37: FOFs | C37: =VLOOKUP($C$30&"-"&B37,Base!$A:$D,4,FALSE) -> 0.05 | D37: =C37*$C$31 -> 17.5
B38: DESENVOLVIMENTO | C38: =VLOOKUP($C$30&"-"&B38,Base!$A:$D,4,FALSE) -> 0.1 | D38: =C38*$C$31 -> 35
B39: HOTELARIAS | C39: =VLOOKUP($C$30&"-"&B39,Base!$A:$D,4,FALSE) -> 0.1 | D39: =C39*$C$31 -> 35
D40: =SUM(D34:D39) -> 350

Sheet Base
A2: CHAVE | B2: PERFIL | C2: TIPO DE FII | D2: %
A3: =B3&"-"&C3 -> Conservador-PAPEL | B3: Conservador | C3: PAPEL | D3: 0.3 | I3: %
A4: =B4&"-"&C4 -> Conservador-TIJOLO | B4: Conservador | C4: TIJOLO | D4: 0.5 | H4: Moderado-TIJOLO | I4: =VLOOKUP(H4,$A:$D,4,FALSE) -> 0.35
A5: =B5&"-"&C5 -> Conservador-HÍBRIDOS | B5: Conservador | C5: HÍBRIDOS | D5: 0.1
A6: =B6&"-"&C6 -> Conservador-FOFs | B6: Conservador | C6: FOFs | D6: 0.1
A7: =B7&"-"&C7 -> Conservador-DESENVOLVIMENTO | B7: Conservador | C7: DESENVOLVIMENTO | D7: 0
A8: =B8&"-"&C8 -> Conservador-HOTELARIAS | B8: Conservador | C8: HOTELARIAS | D8: 0
A9: =B9&"-"&C9 -> Moderado-PAPEL | B9: Moderado | C9: PAPEL | D9: 0.32
A10: =B10&"-"&C10 -> Moderado-TIJOLO | B10: Moderado | C10: TIJOLO | D10: 0.35
A11: =B11&"-"&C11 -> Moderado-HÍBRIDOS | B11: Moderado | C11: HÍBRIDOS | D11: 0.08
A12: =B12&"-"&C12 -> Moderado-FOFs | B12: Moderado | C12: FOFs | D12: 0.05
A13: =B13&"-"&C13 -> Moderado-DESENVOLVIMENTO | B13: Moderado | C13: DESENVOLVIMENTO | D13: 0.1
A14: =B14&"-"&C14 -> Moderado-HOTELARIAS | B14: Moderado | C14: HOTELARIAS | D14: 0.1
A15: =B15&"-"&C15 -> Agressivo-PAPEL | B15: Agressivo | C15: PAPEL | D15: 0.5
A16: =B16&"-"&C16 -> Agressivo-TIJOLO | B16: Agressivo | C16: TIJOLO | D16: 0.1
... A20: =B20&"-"&C20 -> Agressivo-HOTELARIAS | B20: Agressivo | C20: HOTELARIAS | D20: 0.1
